surveiler.py
surveiler-1.0.0.dist-info/LICENSE
surveiler-1.0.0.dist-info/WHEEL
surveiler-1.0.0.dist-info/METADATA
surveiler-1.0.0.dist-info/RECORD
