Metadata-Version: 2.1
Name: surveiler
Version: 1.0.0
Summary: Simple file-system watcher.
Author-email: Pradhyum R <drpradhyum2016@outlook.com>
Classifier: License :: OSI Approved :: MIT License
